Metadata-Version: 2.1
Name: pgsqlx-generator
Version: 1.7.2
Summary: pgsqlx-generator is a model code generator from tables for PgSqlx.
Home-page: https://gitee.com/summry/pgsqlx/blob/master/generator.md
Author: summy
Author-email: xiazhongbiao@126.com
License: UNKNOWN
Keywords: PostgreSQL,PgSqlx,python
Platform: UNKNOWN
Requires-Python: >=3.5
